banjo/__init__.py
banjo/forms.py
banjo/http.py
banjo/models.py
banjo/runner.py
banjo/settings.py
banjo/settings_debug.py
banjo/settings_docs.py
banjo/templates/banjo/api.html
banjo/templates/banjo/api_get.html
banjo/templates/banjo/api_post.html
banjo/templates/banjo/base.html
banjo/urls.py
banjo/views.py
django_banjo-0.9.1.dist-info/LICENSE
django_banjo-0.9.1.dist-info/METADATA
django_banjo-0.9.1.dist-info/WHEEL
django_banjo-0.9.1.dist-info/entry_points.txt
django_banjo-0.9.1.dist-info/RECORD
