Metadata-Version: 2.1
Name: django-banjo
Version: 0.9.1
Summary: A simplified abstraction over django for beginners.
Home-page: https://github.com/cproctor/django-banjo
License: MIT
Author: Chris Proctor
Author-email: chris@chrisproctor.net
Requires-Python: >=3.10,<4.0
Classifier: License :: OSI Approved :: MIT License
Classifier: Programming Language :: Python :: 3
Classifier: Programming Language :: Python :: 3.10
Classifier: Programming Language :: Python :: 3.11
Requires-Dist: django (>=5.1.4,<6.0.0)
Requires-Dist: django-extensions (>=3.2.3,<4.0.0)
Requires-Dist: environ (>=1.0,<2.0)
Project-URL: Documentation, https://django-banjo.readthedocs.io
Project-URL: Repository, https://github.com/cproctor/django-banjo
